timberas/AS1684_dicts.py
timberas/__init__.py
timberas/geometry.py
timberas/material.py
timberas/member.py
timberas/utils.py
timberas/__pycache__/AS1684_dicts.cpython-310.pyc
timberas/__pycache__/__init__.cpython-310.pyc
timberas/__pycache__/geometry.cpython-310.pyc
timberas/__pycache__/material.cpython-310.pyc
timberas/__pycache__/member.cpython-310.pyc
timberas/__pycache__/utils.cpython-310.pyc
timberas/data/__init__.py
timberas/data/material_library.csv
timberas/data/section_library.csv
timberas/data/__pycache__/__init__.cpython-310.pyc
timberas-0.3.0.dist-info/LICENSE.md
timberas-0.3.0.dist-info/METADATA
timberas-0.3.0.dist-info/WHEEL
timberas-0.3.0.dist-info/top_level.txt
timberas-0.3.0.dist-info/RECORD
