Metadata-Version: 2.1
Name: timberas
Version: 0.3.0
Summary: timberas is a Python package for the design of timber structures to relevant Australian Standards
Author-email: Joe Gattas <j.gattas@uq.edu.au>
Project-URL: Homepage, https://github.com/Folded-Structures-Lab/timber-as
Keywords: AS1170,AS1684,timber structures,structural engineering
Classifier: Programming Language :: Python :: 3
Classifier: License :: OSI Approved :: MIT License
Classifier: Operating System :: OS Independent
Requires-Python: >=3.10
License-File: LICENSE.md
Requires-Dist: numpy (>=1.25.0)
Requires-Dist: pandas (>=2.0.2)
